fmcw/190903_rt_fmcw3.py
fmcw/__init__.py
fmcw/adc.py
fmcw/camera.py
fmcw/display.py
fmcw/ftdi.py
fmcw/postprocessing.py
fmcw/preprocessing.py
fmcw-3.2.5.dist-info/LICENSE
fmcw-3.2.5.dist-info/METADATA
fmcw-3.2.5.dist-info/WHEEL
fmcw-3.2.5.dist-info/top_level.txt
fmcw-3.2.5.dist-info/RECORD
