Metadata-Version: 2.1
Name: fmcw
Version: 3.2.5
Summary: Library for fmcw radar
Home-page: https://github.com/AlexBdx/Heli/tree/master/fmcw
Author: Alex Bondoux
Author-email: alexandre.bdx@gmail.com
License: UNKNOWN
Platform: UNKNOWN
Classifier: Programming Language :: Python :: 3
Classifier: License :: OSI Approved :: GNU General Public License v3 (GPLv3)
Classifier: Operating System :: POSIX :: Linux
